Metadata-Version: 2.1
Name: futurepy
Version: 0.0.4
Summary: An unofficial cli version for FutureMe
Home-page: https://github.com/guiszk/futurepy
Author: guiszk
Author-email: guiszk@protonmail.com
License: BSD
Download-URL: https://github.com/guiszk/futurepy/dist/futurepy-0.0.3.tar.gz
Keywords: api,futureme,python
Platform: UNKNOWN
Classifier: Development Status :: 3 - Alpha
Classifier: Intended Audience :: Developers
Classifier: Programming Language :: Python
Classifier: Topic :: Software Development :: Libraries :: Python Modules
Classifier: License :: OSI Approved :: BSD License
Classifier: Programming Language :: Python :: 3
